pg_tuna/__init__.py
pg_tuna/wizard.py
pg_tuna-0.1.1.dist-info/LICENSE
pg_tuna-0.1.1.dist-info/METADATA
pg_tuna-0.1.1.dist-info/WHEEL
pg_tuna-0.1.1.dist-info/entry_points.txt
pg_tuna-0.1.1.dist-info/top_level.txt
pg_tuna-0.1.1.dist-info/RECORD
